webscraping_ai/__init__.py
webscraping_ai/api_client.py
webscraping_ai/api_response.py
webscraping_ai/configuration.py
webscraping_ai/exceptions.py
webscraping_ai/py.typed
webscraping_ai/rest.py
webscraping_ai/api/__init__.py
webscraping_ai/api/account_api.py
webscraping_ai/api/ai_api.py
webscraping_ai/api/html_api.py
webscraping_ai/api/selected_html_api.py
webscraping_ai/api/text_api.py
webscraping_ai/models/__init__.py
webscraping_ai/models/account.py
webscraping_ai/models/error.py
webscraping_ai-3.1.3.dist-info/METADATA
webscraping_ai-3.1.3.dist-info/WHEEL
webscraping_ai-3.1.3.dist-info/top_level.txt
webscraping_ai-3.1.3.dist-info/RECORD
