Metadata-Version: 2.1
Name: webscraping-ai
Version: 3.1.3
Summary: WebScraping.AI
Home-page: https://webscraping.ai
Author: WebScraping.AI Support
Author-email: support@webscraping.ai
Keywords: OpenAPI,OpenAPI-Generator,WebScraping.AI
Requires-Dist: urllib3 <2.1.0,>=1.25.3
Requires-Dist: python-dateutil
Requires-Dist: pydantic >=2
Requires-Dist: typing-extensions >=4.7.1
